cedarscript_ast_parser/__init__.py
cedarscript_ast_parser/cedarscript_ast_parser.py
version/__init__.py
version/_version.py
cedarscript_ast_parser-0.7.0.dist-info/LICENSE
cedarscript_ast_parser-0.7.0.dist-info/METADATA
cedarscript_ast_parser-0.7.0.dist-info/WHEEL
cedarscript_ast_parser-0.7.0.dist-info/top_level.txt
cedarscript_ast_parser-0.7.0.dist-info/RECORD
