Metadata-Version: 2.1
Name: cedarscript-ast-parser
Version: 0.7.0
Summary: A library for parsing and interpreting CEDARScript, a SQL-like language for code analysis and transformations
Author-email: Elifarley <cedarscript@orgecc.com>
License: Apache-2.0
Project-URL: Homepage, https://github.com/CEDARScript/cedarscript-ast-parser-python
Project-URL: Documentation, https://github.com/CEDARScript/cedarscript-ast-parser-python#readme
Project-URL: Repository, https://github.com/CEDARScript/cedarscript-ast-parser-python.git
Project-URL: Bug Tracker, https://github.com/CEDARScript/cedarscript-ast-parser-python/issues
Keywords: parser,ast,cedarscript,code-editing,refactoring,code-analysis,sql-like,ai-assisted-development
Classifier: Programming Language :: Python :: 3
Classifier: Programming Language :: Python :: 3.12
Classifier: License :: OSI Approved :: Apache Software License
Classifier: Operating System :: OS Independent
Classifier: Intended Audience :: Developers
Classifier: Topic :: Software Development :: Libraries :: Python Modules
Classifier: Topic :: Text Processing :: Linguistic
Classifier: Topic :: Software Development :: Code Generators
Classifier: Topic :: Software Development :: Compilers
Requires-Python: >=3.8
License-File: LICENSE
Requires-Dist: cedarscript-grammar>=0.7.0
Provides-Extra: dev
Requires-Dist: pytest>=7.0; extra == "dev"
Requires-Dist: black>=22.0; extra == "dev"
Requires-Dist: isort>=5.0; extra == "dev"
Requires-Dist: flake8>=4.0; extra == "dev"
